plusclouds.py
automation-test-zb/__init__.py
automation-test-zb/__main__.py
automation-test-zb/service.py
automation-test-zb/storage.py
automation-test-zb/module_search/__init__.py
automation-test-zb/module_search/ansible_operations.py
automation-test-zb/module_search/callback_agent.py
automation-test-zb/module_search/service_search.py
automation-test-zb/util/__init__.py
automation-test-zb/util/ssh_keys/__init__.py
automation-test-zb/util/ssh_keys/ssh_key_parser.py
automation_test_zb-0.0.5.dist-info/METADATA
automation_test_zb-0.0.5.dist-info/WHEEL
automation_test_zb-0.0.5.dist-info/licenses/LICENSE
automation_test_zb-0.0.5.dist-info/RECORD
